mwtools/__init__.py
mwtools/rsa_tools/__init__.py
mwtools/rsa_tools/rsa_tools.py
mwtools-0.0.4.dist-info/LICENSE
mwtools-0.0.4.dist-info/METADATA
mwtools-0.0.4.dist-info/WHEEL
mwtools-0.0.4.dist-info/top_level.txt
mwtools-0.0.4.dist-info/RECORD
