Metadata-Version: 2.1
Name: mwtools
Version: 0.0.4
Summary: microwood python tools
Home-page: https://github.com/microwood/mwtools
Author: xuwei
Author-email: microwood.xyz@gmail.com
License: MIT Liense
Platform: UNKNOWN
Requires-Dist: rsa (>=4.0)
